test/__init__.py
test/test_batch_input_v2.py
test/test_default_api.py
test/test_detected_language_v2.py
test/test_entities_batch_result_item_v2.py
test/test_entities_batch_result_v2.py
test/test_entity_record_v2.py
test/test_error_record_v2.py
test/test_error_response.py
test/test_input_v2.py
test/test_internal_error.py
test/test_key_phrase_batch_result_item_v2.py
test/test_key_phrase_batch_result_v2.py
test/test_language_batch_result_item_v2.py
test/test_language_batch_result_v2.py
test/test_match_record_v2.py
test/test_multi_language_batch_input_v2.py
test/test_multi_language_input_v2.py
test/test_object.py
test/test_sentiment_batch_result_item_v2.py
test/test_sentiment_batch_result_v2.py
text_analytics/__init__.py
text_analytics/api_client.py
text_analytics/configuration.py
text_analytics/rest.py
text_analytics/api/__init__.py
text_analytics/api/default_api.py
text_analytics/models/__init__.py
text_analytics/models/batch_input_v2.py
text_analytics/models/detected_language_v2.py
text_analytics/models/entities_batch_result_item_v2.py
text_analytics/models/entities_batch_result_v2.py
text_analytics/models/entity_record_v2.py
text_analytics/models/error_record_v2.py
text_analytics/models/error_response.py
text_analytics/models/input_v2.py
text_analytics/models/internal_error.py
text_analytics/models/key_phrase_batch_result_item_v2.py
text_analytics/models/key_phrase_batch_result_v2.py
text_analytics/models/language_batch_result_item_v2.py
text_analytics/models/language_batch_result_v2.py
text_analytics/models/match_record_v2.py
text_analytics/models/multi_language_batch_input_v2.py
text_analytics/models/multi_language_input_v2.py
text_analytics/models/object.py
text_analytics/models/sentiment_batch_result_item_v2.py
text_analytics/models/sentiment_batch_result_v2.py
text_analytics-1.0.1.dist-info/DESCRIPTION.rst
text_analytics-1.0.1.dist-info/METADATA
text_analytics-1.0.1.dist-info/RECORD
text_analytics-1.0.1.dist-info/WHEEL
text_analytics-1.0.1.dist-info/metadata.json
text_analytics-1.0.1.dist-info/top_level.txt
