Metadata-Version: 2.0
Name: text-analytics
Version: 1.0.1
Summary: Azure Cognitive Services Text Analytics API (v2.0)
Home-page: https://github.com/wmeints/text-analytics
Author-email: willem.meints@gmail.com
License: UNKNOWN
Keywords: Swagger,Text Analytics API (v2.0),Azure,Cognitive Services
Platform: UNKNOWN
Classifier: Intended Audience :: Developers
Classifier: License :: OSI Approved :: Apache Software License
Classifier: Development Status :: 4 - Beta
Requires-Dist: urllib3 (>=1.15)
Requires-Dist: six (>=1.10)
Requires-Dist: certifi
Requires-Dist: python-dateutil
